<links xmlns="urn:ietf:xml:ns:yang:link-traffic">
   <link>
      <link_id>0</link_id>
      <name>aconet</name>
      <color>490099</color>
   </link>
   <link>
      <link_id>1</link_id>
      <name>geant</name>
      <color>008000</color>
   </link>
   <link>
      <link_id>2</link_id>
      <name>nix4</name>
      <color>99a0a9</color>
   </link>
   <link>
      <link_id>3</link_id>
      <name>nix3</name>
      <color>af69bc</color>
   </link>
   <link>
      <link_id>4</link_id>
      <name>pioneer</name>
      <color>ff0000</color>
   </link>
   <link>
      <link_id>5</link_id>
      <name>sanet</name>
      <color>1e90ff</color>
   </link>
   <link>
      <link_id>6</link_id>
      <name>telia</name>
      <color>776655</color>
   </link>
   <link>
      <link_id>7</link_id>
      <name>telia2</name>
      <color>bc9269</color>
   </link>
   <link>
      <link_id>8</link_id>
      <name>amsix</name>
      <color>af99dc</color>
   </link>
</links>
